mentors_event_hub/__init__.py
mentors_event_hub/event_hub.py
mentors_event_hub/event_hub_client.py
mentors_event_hub/azure/__init__.py
mentors_event_hub/azure/azure_service_bus_repository.py
mentors_event_hub/repository/__init__.py
mentors_event_hub/repository/event_repository.py
mentors_event_hub-0.1.3.dist-info/METADATA
mentors_event_hub-0.1.3.dist-info/WHEEL
mentors_event_hub-0.1.3.dist-info/licenses/LICENSE
mentors_event_hub-0.1.3.dist-info/RECORD
