Metadata-Version: 2.4
Name: mentors-event-hub
Version: 0.1.3
Summary: Event hub for centralized exception logging and monitoring
Project-URL: Homepage, https://github.com/Mentorstec/mentors-event-hub
Project-URL: Repository, https://github.com/Mentorstec/mentors-event-hub
Project-URL: Issues, https://github.com/Mentorstec/mentors-event-hub/issues
Project-URL: Documentation, https://github.com/Mentorstec/mentors-event-hub#readme
Author-email: Mentorstec <diego@mentorstec.com.br>
License-Expression: MIT
License-File: LICENSE
Keywords: azure,event-hub,exceptions,logging,monitoring
Classifier: Development Status :: 4 - Beta
Classifier: Intended Audience :: Developers
Classifier: License :: OSI Approved :: MIT License
Classifier: Operating System :: OS Independent
Classifier: Programming Language :: Python :: 3
Classifier: Programming Language :: Python :: 3.8
Classifier: Programming Language :: Python :: 3.9
Classifier: Programming Language :: Python :: 3.10
Classifier: Programming Language :: Python :: 3.11
Classifier: Programming Language :: Python :: 3.12
Classifier: Topic :: System :: Logging
Classifier: Topic :: System :: Monitoring
Requires-Python: >=3.8
Requires-Dist: azure-servicebus>=7.0.0
Provides-Extra: dev
Requires-Dist: black; extra == 'dev'
Requires-Dist: build; extra == 'dev'
Requires-Dist: mypy; extra == 'dev'
Requires-Dist: pytest-cov; extra == 'dev'
Requires-Dist: pytest>=7.0; extra == 'dev'
Requires-Dist: ruff; extra == 'dev'
Requires-Dist: twine; extra == 'dev'
